[
 {
  "user": {
   "username": "tony",
   "avatar": "Owl",
   "name": "Tony Lee"
  },
  "datetime": "2022-01-01T01:00:00.000Z",
  "content": "Hi, welcome to the chatroom!"
 },
 {
  "user": {
   "username": "rabbit",
   "avatar": "Rabbit Face",
   "name": "a rabbit"
  },
  "datetime": "2022-04-17T19:33:52.685Z",
  "content": "Hi everyone"
 },
 {
  "user": {
   "username": "rabbit",
   "avatar": "Rabbit Face",
   "name": "a rabbit"
  },
  "datetime": "2022-04-17T20:32:30.634Z",
  "content": "Test 1"
 },
 {
  "user": {
   "username": "rabbit",
   "avatar": "Rabbit Face",
   "name": "a rabbit"
  },
  "datetime": "2022-04-17T20:33:36.558Z",
  "content": "Test 2"
 },
 {
  "user": {
   "username": "rabbit",
   "avatar": "Rabbit Face",
   "name": "a rabbit"
  },
  "datetime": "2022-04-17T20:38:53.764Z",
  "content": "Test 3"
 },
 {
  "user": {
   "username": "rabbit",
   "avatar": "Rabbit Face",
   "name": "a rabbit"
  },
  "datetime": "2022-04-17T20:40:03.512Z",
  "content": "Test 4"
 },
 {
  "user": {
   "username": "rabbit",
   "avatar": "Rabbit Face",
   "name": "a rabbit"
  },
  "datetime": "2022-04-17T21:26:27.842Z",
  "content": "Test"
 },
 {
  "user": {
   "username": "bird",
   "avatar": "Bird",
   "name": "a bird"
  },
  "datetime": "2022-04-17T21:29:20.392Z",
  "content": "Test"
 }
]